README.md
requirements.txt
setup.py
cvdatasets/__init__.py
cvdatasets/_version.py
cvdatasets/resize.py
cvdatasets.egg-info/PKG-INFO
cvdatasets.egg-info/SOURCES.txt
cvdatasets.egg-info/dependency_links.txt
cvdatasets.egg-info/not-zip-safe
cvdatasets.egg-info/requires.txt
cvdatasets.egg-info/top_level.txt
cvdatasets/annotation/__init__.py
cvdatasets/annotation/base.py
cvdatasets/annotation/files.py
cvdatasets/annotation/mixins/__init__.py
cvdatasets/annotation/mixins/bbox_mixin.py
cvdatasets/annotation/mixins/features_mixin.py
cvdatasets/annotation/mixins/hierarchy_mixin.py
cvdatasets/annotation/mixins/multi_box_mixin.py
cvdatasets/annotation/mixins/parts_mixin.py
cvdatasets/annotation/types/__init__.py
cvdatasets/annotation/types/file_list.py
cvdatasets/annotation/types/folder_annotations.py
cvdatasets/annotation/types/json_annotations.py
cvdatasets/dataset/__init__.py
cvdatasets/dataset/image/__init__.py
cvdatasets/dataset/image/image_wrapper.py
cvdatasets/dataset/image/size.py
cvdatasets/dataset/mixins/__init__.py
cvdatasets/dataset/mixins/base.py
cvdatasets/dataset/mixins/features.py
cvdatasets/dataset/mixins/image_profiler.py
cvdatasets/dataset/mixins/parts.py
cvdatasets/dataset/mixins/reading.py
cvdatasets/dataset/mixins/transform.py
cvdatasets/dataset/mixins/bounding_box/__init__.py
cvdatasets/dataset/mixins/bounding_box/base.py
cvdatasets/dataset/mixins/bounding_box/bbox.py
cvdatasets/dataset/mixins/bounding_box/multi_box.py
cvdatasets/dataset/mixins/chainer_mixins/__init__.py
cvdatasets/dataset/mixins/chainer_mixins/base.py
cvdatasets/dataset/mixins/chainer_mixins/iterator_mixin.py
cvdatasets/dataset/mixins/chainer_mixins/sampling_mixin.py
cvdatasets/dataset/part/__init__.py
cvdatasets/dataset/part/annotation.py
cvdatasets/dataset/part/base.py
cvdatasets/dataset/part/collection.py
cvdatasets/dataset/part/surrogate.py
cvdatasets/utils/__init__.py
cvdatasets/utils/dataset.py
cvdatasets/utils/decorators.py
cvdatasets/utils/image.py
cvdatasets/utils/transforms.py
tests/__init__.py
tests/configs.py
tests/main.py
tests/test_annotations.py
tests/part_tests/__init__.py
tests/part_tests/crop_tests.py
tests/part_tests/surrogate_tests.py