Metadata-Version: 2.1
Name: cvdatasets
Version: 0.12.1
Summary: Wrapper for various computer vision datasets (especially fine-grained)
Home-page: UNKNOWN
Author: Dimitri Korsch
Author-email: korschdima@gmail.com
License: MIT License
Platform: UNKNOWN
